cy/Box.py
cy/__init__.py
cy/cli/__init__.py
cy/cli/cli.py
cyberlib-0.1.1.data/scripts/cy
cyberlib-0.1.1.dist-info/LICENSE
cyberlib-0.1.1.dist-info/METADATA
cyberlib-0.1.1.dist-info/WHEEL
cyberlib-0.1.1.dist-info/entry_points.txt
cyberlib-0.1.1.dist-info/top_level.txt
cyberlib-0.1.1.dist-info/RECORD
