Metadata-Version: 2.1
Name: cyberlib
Version: 0.1.1
Summary: A cool cyber-security python library
Home-page: https://github.com/mind-matrix/cyberlib
Author: Sagnik Modak
Author-email: sagnikmodak1118@gmail.com
License: UNKNOWN
Platform: UNKNOWN
Classifier: Programming Language :: Python :: 3
Classifier: License :: OSI Approved :: MIT License
Classifier: Operating System :: OS Independent
